{
  "word": "concern",
  "definitions": [
    {
      "meaning": "担心或忧虑",
      "usage": "指对某人或某事感到担忧、不安，常用于表达对潜在问题或风险的关注。",
      "collocations": ["express concern", "raise concern", "cause concern"],
      "examples": [
        {
          "scene": "在一个公司的团队会议上，项目经理注意到最近产品质量问题频发，团队成员对此感到不安。",
          "chineseIdea": "项目经理想要告诉大家他对产品质量的担忧，并希望引起大家的重视。",
          "sentenceWithBlank": "The project manager @ @ about the recent decline in product quality during the meeting.",
          "fullEnglishSentence": "The project manager 「expressed concern」 about the recent decline in product quality during the meeting.",
          "chineseTranslation": "项目经理在会议上对近期产品质量下降「表达了担忧」。",
          "chinglishFix": "典型中式英语：He said he is worry about the quality. 纠正：He 「expressed concern」 about the quality."
        },
        {
          "scene": "一位母亲在家长会上听说学校计划减少课外活动的时间，她觉得这可能会影响孩子的全面发展。",
          "chineseIdea": "母亲想要向学校领导提出她对减少课外活动的担忧。",
          "sentenceWithBlank": "The mother @ @ about the decision to reduce extracurricular activities at the parent meeting.",
          "fullEnglishSentence": "The mother 「raised concern」 about the decision to reduce extracurricular activities at the parent meeting.",
          "chineseTranslation": "这位母亲在家长会上对减少课外活动的决定「提出了担忧」。",
          "chinglishFix": "典型中式英语：She said she is afraid about the decision. 纠正：She 「raised concern」 about the decision."
        }
      ]
    },
    {
      "meaning": "关心或关注",
      "usage": "指对某人或某事的情感投入或兴趣，常用于表达对他人的福祉或某事的重视。",
      "collocations": ["show concern", "deep concern", "genuine concern"],
      "examples": [
        {
          "scene": "一位老师发现班上一个平时活泼的学生最近变得沉默寡言，担心他可能遇到了困难。",
          "chineseIdea": "老师想通过行动表示对这个学生的关心，询问他是否需要帮助。",
          "sentenceWithBlank": "The teacher @ @ for the student by asking if he was okay.",
          "fullEnglishSentence": "The teacher 「showed concern」 for the student by asking if he was okay.",
          "chineseTranslation": "老师通过询问学生是否没事来「表达对他的关心」。",
          "chinglishFix": "典型中式英语：The teacher cared the student. 纠正：The teacher 「showed concern」 for the student."
        },
        {
          "scene": "在一次社区活动中，居民们讨论如何保护当地公园的环境问题，大家对此表现出极大的热情。",
          "chineseIdea": "居民们希望强调他们对环境保护的强烈关注和投入。",
          "sentenceWithBlank": "The residents expressed @ @ for the preservation of the local park.",
          "fullEnglishSentence": "The residents expressed 「deep concern」 for the preservation of the local park.",
          "chineseTranslation": "居民们对保护当地公园「表达了深切的关注」。",
          "chinglishFix": "典型中式英语：They have big care for the park. 纠正：They expressed 「deep concern」 for the park."
        }
      ]
    },
    {
      "meaning": "关系或重要性",
      "usage": "指某事与某人或某物之间的关联，或某事对某人的重要性，常用于正式或书面语境。",
      "collocations": ["of concern", "major concern", "primary concern"],
      "examples": [
        {
          "scene": "一家公司正在制定年度预算，管理层讨论哪些问题应该优先解决。",
          "chineseIdea": "管理层想要说明员工培训是他们最重要的事情之一。",
          "sentenceWithBlank": "Employee training is a @ @ for the company this year.",
          "fullEnglishSentence": "Employee training is a 「primary concern」 for the company this year.",
          "chineseTranslation": "员工培训是公司今年的「首要关注点」。",
          "chinglishFix": "典型中式英语：Training is very important thing. 纠正：Training is a 「primary concern」."
        },
        {
          "scene": "在一场国际会议上，发言人讨论全球气候变化对沿海地区的影响。",
          "chineseIdea": "发言人想强调气候变化对沿海社区的直接关联和重要性。",
          "sentenceWithBlank": "Climate change is @ @ to coastal communities around the world.",
          "fullEnglishSentence": "Climate change is 「of concern」 to coastal communities around the world.",
          "chineseTranslation": "气候变化对全球沿海社区「至关重要」。",
          "chinglishFix": "典型中式英语：Climate change is related with communities. 纠正：Climate change is 「of concern」 to communities."
        }
      ]
    }
  ]
}
