{
  "word": "compel",
  "definitions": [
    {
      "meaning": "强迫某人做某事",
      "usage": "通常指通过权威、压力或道德义务迫使某人采取行动，常用于正式或严肃的语境。",
      "collocations": ["compel someone to do something", "compel obedience", "compel attention"],
      "examples": [
        {
          "scene": "在一家公司中，经理发现一名员工经常迟到，影响了团队的工作进度。经理决定采取措施，要求员工按时上班。",
          "chineseIdea": "经理想通过正式的警告信迫使员工遵守公司的时间规定。",
          "sentenceWithBlank": "The manager issued a formal warning to @ @ @ arriving on time.",
          "fullEnglishSentence": "The manager issued a formal warning to 「compel someone to do something」 arriving on time.",
          "chineseTranslation": "经理发布了一封正式警告信，以「强迫某人做某事」按时到达。",
          "chinglishFix": "典型中式英语：'The manager force him must arrive on time.' 纠正：'The manager compelled him to arrive on time.'"
        },
        {
          "scene": "在一场法庭审判中，法官要求证人提供关键证据，以确保案件的公正性。",
          "chineseIdea": "法官希望通过法律权威迫使证人说出真相。",
          "sentenceWithBlank": "The judge used legal authority to @ @ providing crucial evidence.",
          "fullEnglishSentence": "The judge used legal authority to 「compel obedience」 providing crucial evidence.",
          "chineseTranslation": "法官利用法律权威「强迫服从」提供关键证据。",
          "chinglishFix": "典型中式英语：'The judge make him obey to give evidence.' 纠正：'The judge compelled him to provide evidence.'"
        }
      ]
    },
    {
      "meaning": "引起强烈兴趣或注意力",
      "usage": "指某事物因其吸引力或重要性让人不由自主地关注，常用于描述艺术、故事或演讲等。",
      "collocations": ["compel attention", "compel admiration", "compel interest"],
      "examples": [
        {
          "scene": "在一场 TED 演讲中，演讲者通过生动的故事和数据吸引了所有观众的注意力。",
          "chineseIdea": "演讲者的表达方式让观众无法移开视线，深深被吸引。",
          "sentenceWithBlank": "Her vivid storytelling and data @ @ from the entire audience.",
          "fullEnglishSentence": "Her vivid storytelling and data 「compel attention」 from the entire audience.",
          "chineseTranslation": "她生动的故事和数据「引起关注」整个观众群。",
          "chinglishFix": "典型中式英语：'Her story make audience very attract.' 纠正：'Her story compelled the audience’s attention.'"
        },
        {
          "scene": "在一场艺术展览中，一幅画作因其独特的风格和深刻的主题吸引了众多参观者的目光。",
          "chineseIdea": "这幅画的艺术价值让人不由自主地驻足欣赏。",
          "sentenceWithBlank": "The painting’s unique style and depth @ @ from every visitor.",
          "fullEnglishSentence": "The painting’s unique style and depth 「compel admiration」 from every visitor.",
          "chineseTranslation": "这幅画独特的风格和深度「引起赞赏」每一位参观者。",
          "chinglishFix": "典型中式英语：'The painting let people very admire.' 纠正：'The painting compelled admiration from visitors.'"
        }
      ]
    }
  ]
}
